github_token/__init__.py
github_token/__main__.py
github_token-1.0.0.dist-info/DESCRIPTION.rst
github_token-1.0.0.dist-info/METADATA
github_token-1.0.0.dist-info/RECORD
github_token-1.0.0.dist-info/WHEEL
github_token-1.0.0.dist-info/entry_points.txt
github_token-1.0.0.dist-info/metadata.json
github_token-1.0.0.dist-info/top_level.txt
