Metadata-Version: 2.0
Name: github-token
Version: 1.0.0
Summary: Library to create github personal auth token
Home-page: https://github.com/Mariocj89/github-token
Author: Mario Corchero
Author-email: mariocj89@gmail.com
License: MIT
Keywords: github,authorization,tfa,token,twofactor
Platform: UNKNOWN
Classifier: Development Status :: 5 - Production/Stable
Classifier: Intended Audience :: Developers
Classifier: License :: OSI Approved :: MIT License
Classifier: Operating System :: OS Independent
Classifier: Programming Language :: Python
Classifier: Programming Language :: Python :: 3
Classifier: Programming Language :: Python :: 3.4
Classifier: Programming Language :: Python :: 3.5
Classifier: Programming Language :: Python :: 3.6
Requires-Dist: requests
Requires-Dist: six
Requires-Dist: enum34
